[{"id":"6287811078485@s.whatsapp.net","xp":1200,"level":5},{"id":"6289512155924@s.whatsapp.net","xp":680,"level":3},{"id":"6282313549797@s.whatsapp.net","xp":634,"level":3},{"id":"6281391629788@s.whatsapp.net","xp":329,"level":2},{"id":"6285892935752@s.whatsapp.net","xp":301,"level":2},{"id":"6281542301780@s.whatsapp.net","xp":125,"level":1},{"id":"6287824294875@s.whatsapp.net","xp":122,"level":1},{"id":"6285725437572@s.whatsapp.net","xp":117,"level":1},{"id":"6282255491728@s.whatsapp.net","xp":114,"level":1},{"id":"6282137324901@s.whatsapp.net","xp":94,"level":1},{"id":"6285942015818@s.whatsapp.net","xp":90,"level":1},{"id":"6283823923703@s.whatsapp.net","xp":85,"level":1},{"id":"6282137000333@s.whatsapp.net","xp":71,"level":1},{"id":"6285754680757@s.whatsapp.net","xp":41,"level":1},{"id":"628971470094@s.whatsapp.net","xp":36,"level":1},{"id":"62881026163418@s.whatsapp.net","xp":34,"level":1},{"id":"6282323687411@s.whatsapp.net","xp":34,"level":1},{"id":"6283848319727@s.whatsapp.net","xp":31,"level":1},{"id":"6288222431173@s.whatsapp.net","xp":29,"level":1},{"id":"6281219418866@s.whatsapp.net","xp":29,"level":1},{"id":"6282121970795@s.whatsapp.net","xp":26,"level":1},{"id":"6281210344218@s.whatsapp.net","xp":25,"level":1},{"id":"6289603967056@s.whatsapp.net","xp":23,"level":1},{"id":"6282290696661@s.whatsapp.net","xp":22,"level":1},{"id":"6285200309253@s.whatsapp.net","xp":21,"level":1},{"id":"6285159558745@s.whatsapp.net","xp":34,"level":1},{"id":"6281515679916@s.whatsapp.net","xp":20,"level":1},{"id":"6281216093564@s.whatsapp.net","xp":16,"level":1},{"id":"6282139958674@s.whatsapp.net","xp":14,"level":1},{"id":"6287747758341@s.whatsapp.net","xp":14,"level":1},{"id":"6285326835679@s.whatsapp.net","xp":13,"level":1},{"id":"60172738357@s.whatsapp.net","xp":11,"level":1},{"id":"62859153126182@s.whatsapp.net","xp":10,"level":1},{"id":"62895705783090@s.whatsapp.net","xp":7,"level":1},{"id":"62895704406838@s.whatsapp.net","xp":7,"level":1},{"id":"6281244000298@s.whatsapp.net","xp":6,"level":1},{"id":"6285319336071@s.whatsapp.net","xp":6,"level":1},{"id":"6283141990975@s.whatsapp.net","xp":6,"level":1},{"id":"6282351295065@s.whatsapp.net","xp":0,"level":1},{"id":"6285878884150@s.whatsapp.net","xp":0,"level":1},{"id":"628818839108@s.whatsapp.net","xp":0,"level":1},{"id":"6288230373682@s.whatsapp.net","xp":0,"level":1},{"id":"6281225845032@s.whatsapp.net","xp":0,"level":1},{"id":"6289685101257@s.whatsapp.net","xp":0,"level":1},{"id":"62895424038073@s.whatsapp.net","xp":0,"level":1},{"id":"62881026473433@s.whatsapp.net","xp":0,"level":1},{"id":"6285363406398@s.whatsapp.net","xp":0,"level":1},{"id":"6288802665515@s.whatsapp.net","xp":0,"level":1},{"id":"6288220952635@s.whatsapp.net","xp":0,"level":1},{"id":"6285378866882@s.whatsapp.net","xp":0,"level":1},{"id":"6289633451206@s.whatsapp.net","xp":0,"level":1},{"id":"6281328611266@s.whatsapp.net","xp":0,"level":1},{"id":"6283865555452@s.whatsapp.net","xp":0,"level":1},{"id":"6282314666817@s.whatsapp.net","xp":0,"level":1},{"id":"62895385218563@s.whatsapp.net","xp":0,"level":1},{"id":"6287713584036@s.whatsapp.net","xp":0,"level":1},{"id":"6281227901427@s.whatsapp.net","xp":0,"level":1},{"id":"6283137421199@s.whatsapp.net","xp":0,"level":1},{"id":"6281283557569@s.whatsapp.net","xp":0,"level":1},{"id":"6285156835047@s.whatsapp.net","xp":0,"level":1},{"id":"601125669924@s.whatsapp.net","xp":0,"level":1},{"id":"6288242134798@s.whatsapp.net","xp":0,"level":1},{"id":"6282391839752@s.whatsapp.net","xp":0,"level":1},{"id":"6289653418708@s.whatsapp.net","xp":0,"level":1},{"id":"6285230204923@s.whatsapp.net","xp":0,"level":1},{"id":"6281391470802@s.whatsapp.net","xp":0,"level":1},{"id":"6281224648931@s.whatsapp.net","xp":0,"level":1},{"id":"628989277079@s.whatsapp.net","xp":0,"level":1},{"id":"6281524645393@s.whatsapp.net","xp":0,"level":1},{"id":"6282122466105@s.whatsapp.net","xp":0,"level":1},{"id":"6285797826427@s.whatsapp.net","xp":0,"level":1},{"id":"6288220192315@s.whatsapp.net","xp":0,"level":1},{"id":"6282249591043@s.whatsapp.net","xp":0,"level":1},{"id":"6281283672214@s.whatsapp.net","xp":0,"level":1},{"id":"6285712272607@s.whatsapp.net","xp":0,"level":1},{"id":"6288809532237@s.whatsapp.net","xp":0,"level":1},{"id":"62896152383961@s.whatsapp.net","xp":0,"level":1},{"id":"6285852071454@s.whatsapp.net","xp":0,"level":1},{"id":"6285741864621@s.whatsapp.net","xp":0,"level":1},{"id":"6281268992366@s.whatsapp.net","xp":0,"level":1},{"id":"6285879437851@s.whatsapp.net","xp":0,"level":1},{"id":"6283834839414@s.whatsapp.net","xp":0,"level":1},{"id":"6285870565949@s.whatsapp.net","xp":0,"level":1},{"id":"6287801485181@s.whatsapp.net","xp":0,"level":1},{"id":"6289674399673@s.whatsapp.net","xp":0,"level":1},{"id":"6285711920374@s.whatsapp.net","xp":0,"level":1},{"id":"6281259945190@s.whatsapp.net","xp":0,"level":1},{"id":"6285607509020@s.whatsapp.net","xp":0,"level":1},{"id":"6281574478512@s.whatsapp.net","xp":0,"level":1},{"id":"6289529327279@s.whatsapp.net","xp":0,"level":1},{"id":"6282289831437@s.whatsapp.net","xp":0,"level":1},{"id":"6285664255384@s.whatsapp.net","xp":0,"level":1},{"id":"62895364858922@s.whatsapp.net","xp":0,"level":1},{"id":"6285283146108@s.whatsapp.net","xp":0,"level":1},{"id":"6281346150177@s.whatsapp.net","xp":0,"level":1},{"id":"6281239426941@s.whatsapp.net","xp":0,"level":1},{"id":"6281330548772@s.whatsapp.net","xp":0,"level":1},{"id":"6289521162798@s.whatsapp.net","xp":0,"level":1},{"id":"6285868629308@s.whatsapp.net","xp":0,"level":1},{"id":"6285640071927@s.whatsapp.net","xp":0,"level":1},{"id":"6283144204346@s.whatsapp.net","xp":0,"level":1},{"id":"6289512419249@s.whatsapp.net","xp":0,"level":1},{"id":"6281238512572@s.whatsapp.net","xp":0,"level":1},{"id":"6283141964280@s.whatsapp.net","xp":0,"level":1},{"id":"6285871669802@s.whatsapp.net","xp":0,"level":1},{"id":"6285693544713@s.whatsapp.net","xp":0,"level":1},{"id":"6281522882128@s.whatsapp.net","xp":0,"level":1},{"id":"6283176007484@s.whatsapp.net","xp":0,"level":1},{"id":"62881024771992@s.whatsapp.net","xp":0,"level":1},{"id":"6289636536323@s.whatsapp.net","xp":0,"level":1},{"id":"6282289006502@s.whatsapp.net","xp":0,"level":1},{"id":"6285810893601@s.whatsapp.net","xp":0,"level":1},{"id":"6288905593035@s.whatsapp.net","xp":0,"level":1},{"id":"6282271057124@s.whatsapp.net","xp":0,"level":1},{"id":"6288238322031@s.whatsapp.net","xp":0,"level":1},{"id":"6285693105341@s.whatsapp.net","xp":0,"level":1},{"id":"6285692628094@s.whatsapp.net","xp":0,"level":1},{"id":"6281230648429@s.whatsapp.net","xp":0,"level":1},{"id":"6289520029791@s.whatsapp.net","xp":0,"level":1},{"id":"6288219734419@s.whatsapp.net","xp":0,"level":1},{"id":"6285809070886@s.whatsapp.net","xp":0,"level":1},{"id":"6285334574141@s.whatsapp.net","xp":0,"level":1},{"id":"6282124087908@s.whatsapp.net","xp":0,"level":1},{"id":"6281287827813@s.whatsapp.net","xp":0,"level":1},{"id":"6285784641769@s.whatsapp.net","xp":0,"level":1},{"id":"6281280478907@s.whatsapp.net","xp":0,"level":1},{"id":"6285216023503@s.whatsapp.net","xp":0,"level":1},{"id":"6285691970305@s.whatsapp.net","xp":0,"level":1},{"id":"6282247119856@s.whatsapp.net","xp":0,"level":1},{"id":"6288293659915@s.whatsapp.net","xp":0,"level":1},{"id":"6281346575002@s.whatsapp.net","xp":0,"level":1},{"id":"6285738236754@s.whatsapp.net","xp":0,"level":1},{"id":"6285246082231@s.whatsapp.net","xp":0,"level":1},{"id":"6285266569639@s.whatsapp.net","xp":0,"level":1},{"id":"6282286281351@s.whatsapp.net","xp":0,"level":1},{"id":"6287733973572@s.whatsapp.net","xp":0,"level":1},{"id":"62895347062285@s.whatsapp.net","xp":0,"level":1},{"id":"6289682946727@s.whatsapp.net","xp":0,"level":1},{"id":"62895635153633@s.whatsapp.net","xp":0,"level":1},{"id":"6287771947634@s.whatsapp.net","xp":0,"level":1},{"id":"6285796377954@s.whatsapp.net","xp":0,"level":1},{"id":"6281284745140@s.whatsapp.net","xp":0,"level":1},{"id":"6282131434105@s.whatsapp.net","xp":0,"level":1},{"id":"628889893021@s.whatsapp.net","xp":0,"level":1},{"id":"628979491963@s.whatsapp.net","xp":0,"level":1},{"id":"62887435461499@s.whatsapp.net","xp":0,"level":1},{"id":"6283865683498@s.whatsapp.net","xp":0,"level":1},{"id":"6281278725043@s.whatsapp.net","xp":0,"level":1},{"id":"6281211037493@s.whatsapp.net","xp":0,"level":1},{"id":"6285731894174@s.whatsapp.net","xp":0,"level":1},{"id":"62895326106434@s.whatsapp.net","xp":0,"level":1},{"id":"6283162335188@s.whatsapp.net","xp":0,"level":1},{"id":"6282219209651@s.whatsapp.net","xp":0,"level":1},{"id":"6285954711771@s.whatsapp.net","xp":0,"level":1},{"id":"6281259323523@s.whatsapp.net","xp":0,"level":1},{"id":"6285236124648@s.whatsapp.net","xp":0,"level":1},{"id":"6285156578643@s.whatsapp.net","xp":0,"level":1},{"id":"6287829622629@s.whatsapp.net","xp":0,"level":1},{"id":"6282166772979@s.whatsapp.net","xp":0,"level":1},{"id":"6285261094951@s.whatsapp.net","xp":0,"level":1},{"id":"6285854680610@s.whatsapp.net","xp":0,"level":1},{"id":"6289528066000@s.whatsapp.net","xp":0,"level":1},{"id":"6288232733029@s.whatsapp.net","xp":0,"level":1},{"id":"6281515389366@s.whatsapp.net","xp":0,"level":1},{"id":"62895325677273@s.whatsapp.net","xp":0,"level":1},{"id":"6289514010515@s.whatsapp.net","xp":0,"level":1},{"id":"6281358176076@s.whatsapp.net","xp":0,"level":1},{"id":"6285832666013@s.whatsapp.net","xp":0,"level":1},{"id":"6281366896044@s.whatsapp.net","xp":0,"level":1},{"id":"6285942274869@s.whatsapp.net","xp":0,"level":1},{"id":"6285648390994@s.whatsapp.net","xp":0,"level":1},{"id":"6281225185006@s.whatsapp.net","xp":0,"level":1},{"id":"6285768483221@s.whatsapp.net","xp":0,"level":1},{"id":"6282377537348@s.whatsapp.net","xp":0,"level":1},{"id":"6285261094936@s.whatsapp.net","xp":0,"level":1},{"id":"6287769531184@s.whatsapp.net","xp":0,"level":1},{"id":"6289508600123@s.whatsapp.net","xp":0,"level":1},{"id":"628976310380@s.whatsapp.net","xp":0,"level":1},{"id":"6289530050565@s.whatsapp.net","xp":0,"level":1},{"id":"6283161190675@s.whatsapp.net","xp":0,"level":1},{"id":"6289654326956@s.whatsapp.net","xp":0,"level":1},{"id":"6283806604212@s.whatsapp.net","xp":0,"level":1},{"id":"6289506637608@s.whatsapp.net","xp":0,"level":1},{"id":"6282246478432@s.whatsapp.net","xp":0,"level":1},{"id":"6281287868327@s.whatsapp.net","xp":0,"level":1},{"id":"6287700077932@s.whatsapp.net","xp":0,"level":1},{"id":"6283155846924@s.whatsapp.net","xp":0,"level":1},{"id":"6285716639459@s.whatsapp.net","xp":0,"level":1},{"id":"6281807559637@s.whatsapp.net","xp":0,"level":1},{"id":"62895385291051@s.whatsapp.net","xp":0,"level":1},{"id":"6281291145250@s.whatsapp.net","xp":0,"level":1},{"id":"6281241195562@s.whatsapp.net","xp":0,"level":1},{"id":"6285813370954@s.whatsapp.net","xp":0,"level":1},{"id":"6288802840869@s.whatsapp.net","xp":0,"level":1},{"id":"6281315806579@s.whatsapp.net","xp":0,"level":1},{"id":"6285797854557@s.whatsapp.net","xp":0,"level":1},{"id":"62895346257071@s.whatsapp.net","xp":0,"level":1},{"id":"62895337669333@s.whatsapp.net","xp":0,"level":1},{"id":"6281313240698@s.whatsapp.net","xp":0,"level":1},{"id":"6282175906918@s.whatsapp.net","xp":0,"level":1},{"id":"62895366789100@s.whatsapp.net","xp":0,"level":1},{"id":"6285749338645@s.whatsapp.net","xp":0,"level":1},{"id":"6281268191828@s.whatsapp.net","xp":0,"level":1},{"id":"6289524930918@s.whatsapp.net","xp":0,"level":1},{"id":"6281213432110@s.whatsapp.net","xp":0,"level":1},{"id":"6289530247697@s.whatsapp.net","xp":0,"level":1},{"id":"60195645262@s.whatsapp.net","xp":0,"level":1},{"id":"6289685772153@s.whatsapp.net","xp":0,"level":1},{"id":"6285648282081@s.whatsapp.net","xp":0,"level":1},{"id":"62895618741945@s.whatsapp.net","xp":0,"level":1},{"id":"6285718254280@s.whatsapp.net","xp":0,"level":1},{"id":"6281952390737@s.whatsapp.net","xp":0,"level":1},{"id":"6285215672843@s.whatsapp.net","xp":0,"level":1},{"id":"6282310148880@s.whatsapp.net","xp":0,"level":1},{"id":"6281232463541@s.whatsapp.net","xp":0,"level":1},{"id":"6283861340608@s.whatsapp.net","xp":0,"level":1},{"id":"6282118290867@s.whatsapp.net","xp":0,"level":1},{"id":"6282250641536@s.whatsapp.net","xp":0,"level":1},{"id":"6289654270983@s.whatsapp.net","xp":0,"level":1},{"id":"6285386007068@s.whatsapp.net","xp":0,"level":1},{"id":"628982422567@s.whatsapp.net","xp":0,"level":1},{"id":"6283809370692@s.whatsapp.net","xp":0,"level":1},{"id":"6282172486446@s.whatsapp.net","xp":0,"level":1},{"id":"6282274232133@s.whatsapp.net","xp":0,"level":1},{"id":"6285280358869@s.whatsapp.net","xp":0,"level":1},{"id":"6285722302957@s.whatsapp.net","xp":0,"level":1},{"id":"6289505524964@s.whatsapp.net","xp":0,"level":1},{"id":"6288216627743@s.whatsapp.net","xp":0,"level":1},{"id":"6283199398484@s.whatsapp.net","xp":0,"level":1},{"id":"6288289494428@s.whatsapp.net","xp":0,"level":1},{"id":"6281382553270@s.whatsapp.net","xp":0,"level":1},{"id":"628881099033@s.whatsapp.net","xp":0,"level":1},{"id":"6282183297531@s.whatsapp.net","xp":0,"level":1},{"id":"6285328756476@s.whatsapp.net","xp":0,"level":1},{"id":"6285235137266@s.whatsapp.net","xp":0,"level":1},{"id":"6285813431810@s.whatsapp.net","xp":0,"level":1},{"id":"6288216692622@s.whatsapp.net","xp":0,"level":1},{"id":"6285781616915@s.whatsapp.net","xp":0,"level":1},{"id":"6285388794681@s.whatsapp.net","xp":0,"level":1},{"id":"6288225139521@s.whatsapp.net","xp":0,"level":1},{"id":"6285764572160@s.whatsapp.net","xp":0,"level":1},{"id":"6283190723422@s.whatsapp.net","xp":0,"level":1},{"id":"6283816035825@s.whatsapp.net","xp":0,"level":1},{"id":"6285709309483@s.whatsapp.net","xp":0,"level":1},{"id":"6282155004716@s.whatsapp.net","xp":0,"level":1},{"id":"6288227947564@s.whatsapp.net","xp":0,"level":1},{"id":"62895335476020@s.whatsapp.net","xp":0,"level":1},{"id":"6283143417208@s.whatsapp.net","xp":0,"level":1},{"id":"6281337177941@s.whatsapp.net","xp":0,"level":1},{"id":"6283190088098@s.whatsapp.net","xp":0,"level":1},{"id":"6283143482465@s.whatsapp.net","xp":0,"level":1},{"id":"6288707745065@s.whatsapp.net","xp":0,"level":1},{"id":"6282268624337@s.whatsapp.net","xp":0,"level":1},{"id":"6283181414073@s.whatsapp.net","xp":0,"level":1},{"id":"6285860560020@s.whatsapp.net","xp":0,"level":1},{"id":"6283863213202@s.whatsapp.net","xp":0,"level":1},{"id":"6285784286938@s.whatsapp.net","xp":0,"level":1},{"id":"6289515683228@s.whatsapp.net","xp":0,"level":1},{"id":"17076663920@s.whatsapp.net","xp":0,"level":1},{"id":"60174667963@s.whatsapp.net","xp":0,"level":1},{"id":"6281365738772@s.whatsapp.net","xp":0,"level":1},{"id":"6285792195489@s.whatsapp.net","xp":0,"level":1},{"id":"6287743863438@s.whatsapp.net","xp":0,"level":1},{"id":"6287880613523@s.whatsapp.net","xp":0,"level":1},{"id":"6281276123710@s.whatsapp.net","xp":0,"level":1},{"id":"62895422844045@s.whatsapp.net","xp":0,"level":1},{"id":"6283863213203@s.whatsapp.net","xp":0,"level":1},{"id":"6282321276770@s.whatsapp.net","xp":0,"level":1},{"id":"628977930134@s.whatsapp.net","xp":0,"level":1},{"id":"6281386626823@s.whatsapp.net","xp":0,"level":1},{"id":"6289670303650@s.whatsapp.net","xp":0,"level":1},{"id":"6283164113707@s.whatsapp.net","xp":0,"level":1},{"id":"62895390174500@s.whatsapp.net","xp":0,"level":1},{"id":"6282241997784@s.whatsapp.net","xp":0,"level":1},{"id":"6281934141227@s.whatsapp.net","xp":0,"level":1},{"id":"6281111113723@s.whatsapp.net","xp":0,"level":1},{"id":"6285795355813@s.whatsapp.net","xp":0,"level":1},{"id":"6283119512834@s.whatsapp.net","xp":0,"level":1},{"id":"628819593981@s.whatsapp.net","xp":0,"level":1},{"id":"6281229816441@s.whatsapp.net","xp":0,"level":1},{"id":"6282361122990@s.whatsapp.net","xp":0,"level":1},{"id":"601131897984@s.whatsapp.net","xp":0,"level":1},{"id":"6289525341416@s.whatsapp.net","xp":0,"level":1},{"id":"6281809422420@s.whatsapp.net","xp":0,"level":1},{"id":"6281325944421@s.whatsapp.net","xp":0,"level":1},{"id":"6285810692241@s.whatsapp.net","xp":0,"level":1},{"id":"6282375029838@s.whatsapp.net","xp":0,"level":1},{"id":"6285704583862@s.whatsapp.net","xp":0,"level":1},{"id":"6288221596866@s.whatsapp.net","xp":0,"level":1},{"id":"6285745448028@s.whatsapp.net","xp":0,"level":1},{"id":"6282193098916@s.whatsapp.net","xp":0,"level":1},{"id":"6281645464639@s.whatsapp.net","xp":0,"level":1},{"id":"6281393154140@s.whatsapp.net","xp":0,"level":1},{"id":"6281315061490@s.whatsapp.net","xp":0,"level":1},{"id":"6285213563769@s.whatsapp.net","xp":0,"level":1},{"id":"6285711247101@s.whatsapp.net","xp":0,"level":1},{"id":"6285719137809@s.whatsapp.net","xp":0,"level":1},{"id":"6281289372202@s.whatsapp.net","xp":0,"level":1},{"id":"6287799648367@s.whatsapp.net","xp":0,"level":1},{"id":"6285216970494@s.whatsapp.net","xp":0,"level":1},{"id":"6282114020981@s.whatsapp.net","xp":0,"level":1},{"id":"6285822515051@s.whatsapp.net","xp":0,"level":1},{"id":"6282184242451@s.whatsapp.net","xp":0,"level":1},{"id":"6281250750100@s.whatsapp.net","xp":0,"level":1},{"id":"6285709668107@s.whatsapp.net","xp":0,"level":1},{"id":"6285821814788@s.whatsapp.net","xp":0,"level":1},{"id":"6285351243507@s.whatsapp.net","xp":0,"level":1},{"id":"6285791953350@s.whatsapp.net","xp":0,"level":1},{"id":"6282134525406@s.whatsapp.net","xp":0,"level":1},{"id":"628994950568@s.whatsapp.net","xp":0,"level":1},{"id":"6285156126771@s.whatsapp.net","xp":0,"level":1},{"id":"6281292804495@s.whatsapp.net","xp":0,"level":1},{"id":"62895322186236@s.whatsapp.net","xp":0,"level":1},{"id":"6285875063235@s.whatsapp.net","xp":0,"level":1},{"id":"6285348487102@s.whatsapp.net","xp":0,"level":1},{"id":"6289523786578@s.whatsapp.net","xp":0,"level":1},{"id":"6285795612696@s.whatsapp.net","xp":0,"level":1},{"id":"6285799824258@s.whatsapp.net","xp":0,"level":1},{"id":"6285877513471@s.whatsapp.net","xp":0,"level":1},{"id":"6285752507033@s.whatsapp.net","xp":0,"level":1},{"id":"17159942588@s.whatsapp.net","xp":0,"level":1},{"id":"6281393168727@s.whatsapp.net","xp":0,"level":1},{"id":"6283142027933@s.whatsapp.net","xp":0,"level":1},{"id":"62895337595213@s.whatsapp.net","xp":0,"level":1},{"id":"6281233771174@s.whatsapp.net","xp":0,"level":1},{"id":"6283817452008@s.whatsapp.net","xp":0,"level":1},{"id":"6281477048715@s.whatsapp.net","xp":0,"level":1},{"id":"6282316581773@s.whatsapp.net","xp":0,"level":1},{"id":"6282220748194@s.whatsapp.net","xp":0,"level":1},{"id":"6283819534969@s.whatsapp.net","xp":0,"level":1},{"id":"6283865829393@s.whatsapp.net","xp":0,"level":1},{"id":"6281522750319@s.whatsapp.net","xp":0,"level":1},{"id":"6283198551303@s.whatsapp.net","xp":0,"level":1},{"id":"6288976737161@s.whatsapp.net","xp":0,"level":1},{"id":"6282370233331@s.whatsapp.net","xp":0,"level":1},{"id":"6282157740415@s.whatsapp.net","xp":0,"level":1},{"id":"6281264973563@s.whatsapp.net","xp":0,"level":1},{"id":"6288246275787@s.whatsapp.net","xp":0,"level":1},{"id":"6281330626804@s.whatsapp.net","xp":0,"level":1},{"id":"6285828102052@s.whatsapp.net","xp":0,"level":1},{"id":"62895341744890@s.whatsapp.net","xp":0,"level":1},{"id":"62895337399574@s.whatsapp.net","xp":0,"level":1},{"id":"6287717594160@s.whatsapp.net","xp":0,"level":1},{"id":"56921707411@s.whatsapp.net","xp":0,"level":1},{"id":"6285803758702@s.whatsapp.net","xp":0,"level":1},{"id":"6283839292844@s.whatsapp.net","xp":0,"level":1},{"id":"6283821481743@s.whatsapp.net","xp":0,"level":1},{"id":"62895391677224@s.whatsapp.net","xp":0,"level":1},{"id":"6281310890493@s.whatsapp.net","xp":0,"level":1},{"id":"6281292419823@s.whatsapp.net","xp":0,"level":1},{"id":"62882019231337@s.whatsapp.net","xp":0,"level":1},{"id":"6289601623707@s.whatsapp.net","xp":0,"level":1},{"id":"6281932558604@s.whatsapp.net","xp":0,"level":1},{"id":"628985146329@s.whatsapp.net","xp":0,"level":1},{"id":"6282135817096@s.whatsapp.net","xp":0,"level":1},{"id":"6281261732023@s.whatsapp.net","xp":0,"level":1},{"id":"6285390302544@s.whatsapp.net","xp":0,"level":1},{"id":"6289683274900@s.whatsapp.net","xp":0,"level":1},{"id":"6282219671469@s.whatsapp.net","xp":0,"level":1},{"id":"6289649800803@s.whatsapp.net","xp":0,"level":1},{"id":"62856245071820@s.whatsapp.net","xp":0,"level":1},{"id":"6285770542728@s.whatsapp.net","xp":0,"level":1},{"id":"6281318460097@s.whatsapp.net","xp":0,"level":1},{"id":"6285791491912@s.whatsapp.net","xp":0,"level":1},{"id":"6285257184514@s.whatsapp.net","xp":0,"level":1},{"id":"6285281712318@s.whatsapp.net","xp":0,"level":1},{"id":"6287730284527@s.whatsapp.net","xp":0,"level":1},{"id":"6283128734012@s.whatsapp.net","xp":0,"level":1},{"id":"6289637434755@s.whatsapp.net","xp":0,"level":1},{"id":"6285755053056@s.whatsapp.net","xp":0,"level":1},{"id":"6285881574360@s.whatsapp.net","xp":0,"level":1},{"id":"6281293982628@s.whatsapp.net","xp":0,"level":1},{"id":"6281352002918@s.whatsapp.net","xp":0,"level":1},{"id":"6289653400101@s.whatsapp.net","xp":0,"level":1},{"id":"62895340096631@s.whatsapp.net","xp":0,"level":1},{"id":"6283803435580@s.whatsapp.net","xp":0,"level":1},{"id":"6285793482201@s.whatsapp.net","xp":0,"level":1},{"id":"628983583288@s.whatsapp.net","xp":0,"level":1},{"id":"628889949943@s.whatsapp.net","xp":0,"level":1},{"id":"6285655286474@s.whatsapp.net","xp":0,"level":1},{"id":"6285343977719@s.whatsapp.net","xp":0,"level":1},{"id":"6281227397795@s.whatsapp.net","xp":0,"level":1},{"id":"6289501768918@s.whatsapp.net","xp":0,"level":1},{"id":"6281345544146@s.whatsapp.net","xp":0,"level":1},{"id":"6281298611025@s.whatsapp.net","xp":0,"level":1},{"id":"62895324883708@s.whatsapp.net","xp":0,"level":1},{"id":"6283188534660@s.whatsapp.net","xp":0,"level":1},{"id":"62895618293141@s.whatsapp.net","xp":0,"level":1},{"id":"6287880809244@s.whatsapp.net","xp":0,"level":1},{"id":"6282154595812@s.whatsapp.net","xp":0,"level":1},{"id":"6282126549617@s.whatsapp.net","xp":0,"level":1},{"id":"6285943537780@s.whatsapp.net","xp":0,"level":1},{"id":"6287794137231@s.whatsapp.net","xp":0,"level":1},{"id":"6285877223326@s.whatsapp.net","xp":0,"level":1},{"id":"62882003362616@s.whatsapp.net","xp":0,"level":1},{"id":"6289514199310@s.whatsapp.net","xp":0,"level":1},{"id":"6283807060210@s.whatsapp.net","xp":0,"level":1},{"id":"6285705891807@s.whatsapp.net","xp":0,"level":1},{"id":"62895338445194@s.whatsapp.net","xp":0,"level":1},{"id":"62887437153241@s.whatsapp.net","xp":0,"level":1},{"id":"6285972595828@s.whatsapp.net","xp":0,"level":1},{"id":"6288802926187@s.whatsapp.net","xp":0,"level":1},{"id":"6285959375675@s.whatsapp.net","xp":0,"level":1},{"id":"6285821927699@s.whatsapp.net","xp":0,"level":1},{"id":"6281527624974@s.whatsapp.net","xp":0,"level":1},{"id":"6289517832192@s.whatsapp.net","xp":0,"level":1},{"id":"6285754337101@s.whatsapp.net","xp":0,"level":1},{"id":"628995054555@s.whatsapp.net","xp":0,"level":1},{"id":"6285890209970@s.whatsapp.net","xp":0,"level":1},{"id":"6282391525040@s.whatsapp.net","xp":0,"level":1},{"id":"6282350935131@s.whatsapp.net","xp":0,"level":1},{"id":"6285780907616@s.whatsapp.net","xp":0,"level":1},{"id":"6287776010440@s.whatsapp.net","xp":0,"level":1},{"id":"6285349846266@s.whatsapp.net","xp":0,"level":1},{"id":"6289531969932@s.whatsapp.net","xp":0,"level":1},{"id":"6283134748126@s.whatsapp.net","xp":0,"level":1},{"id":"6285389157005@s.whatsapp.net","xp":0,"level":1},{"id":"6287774057716@s.whatsapp.net","xp":0,"level":1},{"id":"6285608538413@s.whatsapp.net","xp":0,"level":1},{"id":"62895322084090@s.whatsapp.net","xp":0,"level":1},{"id":"6283141338404@s.whatsapp.net","xp":0,"level":1},{"id":"6288238009870@s.whatsapp.net","xp":0,"level":1},{"id":"62818994266@s.whatsapp.net","xp":0,"level":1},{"id":"6282136496733@s.whatsapp.net","xp":0,"level":1},{"id":"62895601889012@s.whatsapp.net","xp":0,"level":1},{"id":"6283895023873@s.whatsapp.net","xp":0,"level":1},{"id":"6285606089982@s.whatsapp.net","xp":0,"level":1},{"id":"6283874522759@s.whatsapp.net","xp":0,"level":1},{"id":"6289691705401@s.whatsapp.net","xp":0,"level":1},{"id":"6285724182166@s.whatsapp.net","xp":0,"level":1},{"id":"62895336753324@s.whatsapp.net","xp":0,"level":1},{"id":"6285789409830@s.whatsapp.net","xp":0,"level":1},{"id":"6283140155545@s.whatsapp.net","xp":0,"level":1},{"id":"6282129831230@s.whatsapp.net","xp":0,"level":1},{"id":"6283815327421@s.whatsapp.net","xp":0,"level":1},{"id":"6282141068985@s.whatsapp.net","xp":0,"level":1},{"id":"6281214499100@s.whatsapp.net","xp":0,"level":1},{"id":"6281242298369@s.whatsapp.net","xp":0,"level":1},{"id":"6283147076972@s.whatsapp.net","xp":0,"level":1},{"id":"6285727010451@s.whatsapp.net","xp":0,"level":1},{"id":"6281369240050@s.whatsapp.net","xp":0,"level":1},{"id":"6288213794601@s.whatsapp.net","xp":0,"level":1},{"id":"6281313485823@s.whatsapp.net","xp":0,"level":1},{"id":"6283175745220@s.whatsapp.net","xp":0,"level":1},{"id":"6281283358799@s.whatsapp.net","xp":0,"level":1},{"id":"6283155892791@s.whatsapp.net","xp":0,"level":1},{"id":"6283821279354@s.whatsapp.net","xp":0,"level":1},{"id":"6281545411472@s.whatsapp.net","xp":0,"level":1},{"id":"6289502839997@s.whatsapp.net","xp":0,"level":1},{"id":"6283180531337@s.whatsapp.net","xp":0,"level":1},{"id":"6282376766307@s.whatsapp.net","xp":0,"level":1},{"id":"6287842239808@s.whatsapp.net","xp":0,"level":1},{"id":"6283897130627@s.whatsapp.net","xp":0,"level":1},{"id":"6287779014677@s.whatsapp.net","xp":0,"level":1},{"id":"6285668221961@s.whatsapp.net","xp":0,"level":1},{"id":"6285883264093@s.whatsapp.net","xp":0,"level":1},{"id":"6285727551049@s.whatsapp.net","xp":0,"level":1},{"id":"6285713422789@s.whatsapp.net","xp":0,"level":1},{"id":"6285811544459@s.whatsapp.net","xp":0,"level":1},{"id":"6282181951702@s.whatsapp.net","xp":0,"level":1},{"id":"6285747371987@s.whatsapp.net","xp":0,"level":1},{"id":"6282341098816@s.whatsapp.net","xp":0,"level":1},{"id":"6285842528355@s.whatsapp.net","xp":0,"level":1},{"id":"6288221339938@s.whatsapp.net","xp":0,"level":1},{"id":"6285883244102@s.whatsapp.net","xp":0,"level":1},{"id":"6282288970366@s.whatsapp.net","xp":0,"level":1},{"id":"6283838050752@s.whatsapp.net","xp":0,"level":1},{"id":"6285640587034@s.whatsapp.net","xp":0,"level":1},{"id":"6285298014548@s.whatsapp.net","xp":0,"level":1},{"id":"6289508891459@s.whatsapp.net","xp":0,"level":1},{"id":"6283873032139@s.whatsapp.net","xp":0,"level":1},{"id":"6285748631448@s.whatsapp.net","xp":0,"level":1},{"id":"6285725143431@s.whatsapp.net","xp":0,"level":1},{"id":"6289503308716@s.whatsapp.net","xp":0,"level":1},{"id":"6285883124469@s.whatsapp.net","xp":0,"level":1},{"id":"6285772240582@s.whatsapp.net","xp":0,"level":1},{"id":"6285836975229@s.whatsapp.net","xp":0,"level":1},{"id":"6283169379166@s.whatsapp.net","xp":0,"level":1},{"id":"6287805815207@s.whatsapp.net","xp":0,"level":1},{"id":"6289637637004@s.whatsapp.net","xp":0,"level":1},{"id":"6285824126796@s.whatsapp.net","xp":0,"level":1},{"id":"6282112021859@s.whatsapp.net","xp":0,"level":1},{"id":"6281353100956@s.whatsapp.net","xp":0,"level":1},{"id":"6283150486610@s.whatsapp.net","xp":0,"level":1},{"id":"6282296177010@s.whatsapp.net","xp":0,"level":1},{"id":"6282331243776@s.whatsapp.net","xp":0,"level":1},{"id":"6287721435286@s.whatsapp.net","xp":0,"level":1},{"id":"6282362559029@s.whatsapp.net","xp":0,"level":1},{"id":"6285774142551@s.whatsapp.net","xp":0,"level":1},{"id":"6287822264717@s.whatsapp.net","xp":0,"level":1},{"id":"6287778898546@s.whatsapp.net","xp":0,"level":1},{"id":"6287857180075@s.whatsapp.net","xp":0,"level":1},{"id":"67076658529@s.whatsapp.net","xp":0,"level":1},{"id":"201277647593@s.whatsapp.net","xp":0,"level":1},{"id":"919126367268@s.whatsapp.net","xp":0,"level":1},{"id":"6289660579923@s.whatsapp.net","xp":0,"level":1},{"id":"6285932830162@s.whatsapp.net","xp":0,"level":1},{"id":"6281953990104@s.whatsapp.net","xp":0,"level":1},{"id":"6282338259783@s.whatsapp.net","xp":0,"level":1},{"id":"6287769119852@s.whatsapp.net","xp":0,"level":1},{"id":"62895354333554@s.whatsapp.net","xp":0,"level":1},{"id":"6282377261274@s.whatsapp.net","xp":0,"level":1},{"id":"6282172679781@s.whatsapp.net","xp":0,"level":1},{"id":"6285289604987@s.whatsapp.net","xp":0,"level":1},{"id":"6282175647877@s.whatsapp.net","xp":0,"level":1},{"id":"6283801649828@s.whatsapp.net","xp":0,"level":1},{"id":"6289613932361@s.whatsapp.net","xp":0,"level":1},{"id":"6285830405964@s.whatsapp.net","xp":0,"level":1},{"id":"6285860732815@s.whatsapp.net","xp":0,"level":1},{"id":"6281231859441@s.whatsapp.net","xp":0,"level":1},{"id":"6285745092950@s.whatsapp.net","xp":0,"level":1},{"id":"62895392617964@s.whatsapp.net","xp":0,"level":1},{"id":"6288232753563@s.whatsapp.net","xp":0,"level":1},{"id":"6281268082794@s.whatsapp.net","xp":0,"level":1},{"id":"6285828974552@s.whatsapp.net","xp":0,"level":1},{"id":"6287867192064@s.whatsapp.net","xp":0,"level":1},{"id":"6285803628661@s.whatsapp.net","xp":0,"level":1},{"id":"6282251421902@s.whatsapp.net","xp":0,"level":1},{"id":"62895347014876@s.whatsapp.net","xp":0,"level":1},{"id":"6285863447577@s.whatsapp.net","xp":0,"level":1},{"id":"6283896232427@s.whatsapp.net","xp":0,"level":1},{"id":"6289526565910@s.whatsapp.net","xp":0,"level":1},{"id":"6285782229433@s.whatsapp.net","xp":0,"level":1},{"id":"6283110461377@s.whatsapp.net","xp":0,"level":1},{"id":"6281262839361@s.whatsapp.net","xp":0,"level":1},{"id":"6281311888098@s.whatsapp.net","xp":0,"level":1}]